{
    "launchers": [
        {
            "type": "standard",
            "rom_path": "/home/karl/SeraphStore/Games/WiiU",
            "scan_pattern": "*/vol/code/*.rpx",
            "cmd": "wine /home/karl/Apps/Cemu/Cemu.exe -f -a %CEMU_ACCOUNT% -g %ROM%",
            "platform": "wii_u",
            "comment": "scan_pattern searches recursively for .rpx files in game subdirectories"
        },
        {
            "type": "standard",
            "rom_path": "/home/karl/SeraphStore/Games/PS3",
            "scan_pattern": "*/PS3_GAME/USRDIR/EBOOT.BIN",
            "cmd": "rpcs3 --no-gui %ROM%",
            "platform": "playstation_3",
            "comment": "scan_pattern finds EBOOT.BIN files in PS3 game folders"
        },
        {
            "type": "standard",
            "rom_path": "/home/karl/SeraphStore/Games/Super Console/psx",
            "extension": ".cue,.m3u",
            "cmd": "retroarch -f --appendconfig=%RETROARCH_CONFIG% -L /home/karl/.config/retroarch/cores/mednafen_psx_hw_libretro.so %ROM%",
            "platform": "playstation"
        },
        {
            "type": "standard",
            "rom_path": "/home/karl/SeraphStore/Games/Super Console/gc",
            "extension": ".iso",
            "cmd": "dolphin-emu-nogui -C \"Dolphin.Core.MemcardAPath=%DOLPHIN_CARD%\" %ROM%",
            "platform": "gamecube"
        },
        {
            "type": "standard",
            "rom_path": "/home/karl/SeraphStore/Games/Super Console/nes",
            "extension": ".zip",
            "cmd": "retroarch -f --appendconfig=%RETROARCH_CONFIG% -L /home/karl/.config/retroarch/cores/nestopia_libretro.so %ROM%",
            "platform": "nintendo_entertainment_system"
        },
        {
            "type": "standard",
            "rom_path": "/home/karl/SeraphStore/Games/Super Console/snes",
            "extension": ".zip",
            "cmd": "retroarch -f --appendconfig=%RETROARCH_CONFIG% -L /home/karl/.config/retroarch/cores/mednafen_snes_libretro.so %ROM%",
            "platform": "super_nintendo_entertainment_system"
        },
        {
            "type": "steam"
        },
        {
            "type": "standard",
            "rom_path": "/home/karl/SeraphStore/Games/SCUMM",
            "scan_pattern": "DIRECTORY",
            "cmd": "scummvm --auto-detect --path=%ROM%",
            "platform": "scummvm",
            "comment": "scan_pattern=DIRECTORY scans for subdirectories instead of files"
        },
        {
            "type": "standard",
            "rom_path": "/home/karl/.local/share/Vita3K/ux0/app",
            "scan_pattern": "{*}/eboot.bin",
            "match_field": "title_id",
            "path_is_match_string": true,
            "cmd": "/home/karl/Apps/Vita3K.AppImage -r %ROM%",
            "platform": "playstation_vita",
            "comment": "{*} extracts folder name for matching, match_field uses title_id instead of game name, path_is_match_string uses extracted ID as ROM path"
        }
    ],
    "users": [
        {
            "name": "Karl",
            "email": "my@email.com",
            "avatar": "/home/karl/Pictures/avatars/karl.jpg",

            "comment": "You can define ANY custom fields below and use them in launchers with %FIELD_NAME%",
            "cemu_account": "80000001",
            "retroarch_config": "/home/karl/.offblast/karl_ra.cfg",
            "save_path": "/home/karl/SeraphStore/Games/Super Console/saves/karl/",
            "dolphin_card": "/home/karl/SeraphStore/Games/Super Console/saves/karl/dolphin/karl.USA.raw",
            "wine_prefix": "/home/karl/.wine-gaming",
            "rpcs3_account": "00000002",
            "yuzu_user_index": "1",
            "my_custom_setting": "any_value_you_want",
            "literally_anything": "will_be_available_as_%LITERALLY_ANYTHING%"
        }, {
            "name": "Cloud",
            "email": "my@email.com",
            "avatar": "/home/karl/Pictures/avatars/cloud.jpg",
            "cemu_account": "80000002",
            "retroarch_config": "/home/karl/.offblast/cloud_ra.cfg",
            "save_path": "/home/karl/SeraphStore/Games/Super Console/saves/cloud/",
            "dolphin_card": "/home/karl/SeraphStore/Games/Super Console/saves/cloud/dolphin/USA.raw"
        }, {
            "name": "Pai",
            "email": "my@email.com",
            "avatar": "/home/karl/Pictures/avatars/pai.jpg",
            "cemu_account": "80000003",
            "retroarch_config": "/home/karl/.offblast/pai_ra.cfg",
            "save_path": "/home/karl/SeraphStore/Games/Super Console/saves/pai/",
            "dolphin_card": "/home/karl/SeraphStore/Games/Super Console/saves/pai/dolphin/USA.raw"
        }
    ],
    "opengamedb": "/home/karl/.offblast/opengamedb",
    "comment_opengamedb": "AppImage automatically installs/updates database here. Change path if using custom database location.",
    "playtime_path": "/home/karl/SeraphStore/Games/Super Console/saves/",

    "steam": {
        "api_key": "YOUR_STEAM_API_KEY",
        "steam_id": "YOUR_STEAM_ID_64"
    },
    "comment_steam": "Optional: Get API key at https://steamcommunity.com/dev/apikey, find your Steam ID at steamid.io. Enables showing all owned games (not just installed).",

    "steamgriddb_api_key": "",
    "comment_steamgriddb": "Optional: Get API key at https://www.steamgriddb.com/profile/preferences/api. Enables browsing and selecting custom covers from context menu."
}
